diligence_fuzzing-0.13.4.dist-info/licenses/AUTHORS.rst
diligence_fuzzing-0.13.4.dist-info/licenses/LICENSE
fuzzing_cli/__init__.py
fuzzing_cli/cli.py
fuzzing_cli/util.py
fuzzing_cli/fuzz/__init__.py
fuzzing_cli/fuzz/arm.py
fuzzing_cli/fuzz/disarm.py
fuzzing_cli/fuzz/exceptions.py
fuzzing_cli/fuzz/faas.py
fuzzing_cli/fuzz/foundry_tests.py
fuzzing_cli/fuzz/fuzz_config.py
fuzzing_cli/fuzz/fuzzing_lessons.py
fuzzing_cli/fuzz/quickcheck.py
fuzzing_cli/fuzz/run.py
fuzzing_cli/fuzz/scribble.py
fuzzing_cli/fuzz/solidity.py
fuzzing_cli/fuzz/version.py
fuzzing_cli/fuzz/analytics/__init__.py
fuzzing_cli/fuzz/analytics/session.py
fuzzing_cli/fuzz/config/__init__.py
fuzzing_cli/fuzz/config/auth.py
fuzzing_cli/fuzz/config/generate.py
fuzzing_cli/fuzz/config/options.py
fuzzing_cli/fuzz/config/pytimer.py
fuzzing_cli/fuzz/config/template.py
fuzzing_cli/fuzz/config/utils.py
fuzzing_cli/fuzz/corpus/__init__.py
fuzzing_cli/fuzz/corpus/repository.py
fuzzing_cli/fuzz/ide/__init__.py
fuzzing_cli/fuzz/ide/brownie.py
fuzzing_cli/fuzz/ide/dapptools.py
fuzzing_cli/fuzz/ide/foundry.py
fuzzing_cli/fuzz/ide/generic.py
fuzzing_cli/fuzz/ide/hardhat.py
fuzzing_cli/fuzz/ide/repository.py
fuzzing_cli/fuzz/ide/truffle.py
fuzzing_cli/fuzz/lessons/__init__.py
fuzzing_cli/fuzz/quickcheck_lib/__init__.py
fuzzing_cli/fuzz/quickcheck_lib/quickcheck.py
fuzzing_cli/fuzz/quickcheck_lib/utils.py
fuzzing_cli/fuzz/rpc/__init__.py
fuzzing_cli/fuzz/rpc/generic.py
fuzzing_cli/fuzz/rpc/rpc.py
fuzzing_cli/fuzz/storage/__init__.py
fuzzing_cli/fuzz/types/__init__.py
fuzzing_cli/fuzz/types/ide.py
fuzzing_cli/fuzz/types/lessons.py
fuzzing_cli/fuzz/types/rpc.py
fuzzing_cli/fuzz/utils/__init__.py
tests/testdata/__init__.py
tests/testdata/brownie-artifact.json
tests/testdata/dapptools_artifact.json
tests/testdata/ganache-all-blocks.json
tests/testdata/hardhat-artifact-different-contract-name.json
tests/testdata/hardhat-artifact.json
tests/testdata/hardhat-build-info-artifact-1.json
tests/testdata/hardhat-build-info-artifact.json
tests/testdata/truffle-artifact.json
tests/testdata/brownie_project/README.md
tests/testdata/foundry_project/artifacts/out/build-info/035e6a793441ce12cc390e0cd008a242.json
diligence_fuzzing-0.13.4.dist-info/METADATA
diligence_fuzzing-0.13.4.dist-info/WHEEL
diligence_fuzzing-0.13.4.dist-info/entry_points.txt
diligence_fuzzing-0.13.4.dist-info/top_level.txt
diligence_fuzzing-0.13.4.dist-info/RECORD
