Metadata-Version: 2.4
Name: diligence-fuzzing
Version: 0.13.4
Summary: A command line interface for the Diligence Fuzzing API
Home-page: https://github.com/ConsenSys/diligence-fuzzing
Author: Dominik Muhs, João Santos
Author-email: joao.santos@consensys.net
License: Apache-2.0 License
Keywords: diligence-fuzzing
Classifier: Development Status :: 4 - Beta
Classifier: License :: OSI Approved :: Apache Software License
Classifier: Natural Language :: English
Classifier: Intended Audience :: Developers
Classifier: Intended Audience :: Education
Classifier: Intended Audience :: Information Technology
Classifier: Topic :: Security
Classifier: Topic :: Software Development :: Libraries :: Python Modules
Classifier: Topic :: Software Development :: Quality Assurance
Classifier: Topic :: Terminals :: Terminal Emulators/X Terminals
Classifier: Topic :: Utilities
Classifier: Typing :: Typed
Classifier: Programming Language :: Python :: 3
Classifier: Programming Language :: Python :: 3.8
Classifier: Programming Language :: Python :: 3.9
Classifier: Programming Language :: Python :: 3.10
Classifier: Programming Language :: Python :: 3.11
Classifier: Programming Language :: Python :: Implementation :: PyPy
Requires-Python: >=3.8,<4
License-File: LICENSE
License-File: AUTHORS.rst
Requires-Dist: Click==8.1.3
Requires-Dist: Jinja2==3.1.4
Requires-Dist: PyYAML==6.0.1
Requires-Dist: inquirer==3.4.0
Requires-Dist: typing_extensions>=4.5.0
Requires-Dist: ruamel.yaml==0.17.2
Requires-Dist: requests==2.32.2
Requires-Dist: pycryptodome==3.20.0
Requires-Dist: rlp==4.0.1
Requires-Dist: py-solc-x==1.1.1
Requires-Dist: cbor2==5.4.6
Requires-Dist: toml==0.10.2
Requires-Dist: pydantic[dotenv]~=1.10
Requires-Dist: elastic-apm==6.18.0
Requires-Dist: appdirs==1.4.4
Dynamic: author
Dynamic: author-email
Dynamic: classifier
Dynamic: description
Dynamic: description-content-type
Dynamic: home-page
Dynamic: keywords
Dynamic: license
Dynamic: license-file
Dynamic: requires-dist
Dynamic: requires-python
Dynamic: summary
